blt/__init__.py
blt/base.py
blt/pipeline/__init__.py
blt/pipeline/rvc_ktv_pipeline.py
blt/synthesizer/__init__.py
blt/synthesizer/audio_mixer.py
blt/synthesizer/lyrics_aligner.py
blt/synthesizer/vocal_separator.py
blt/synthesizer/voice_converter.py
blt/synthesizer/video_generator/__init__.py
blt/synthesizer/video_generator/ktv_video_generator.py
blt/synthesizer/video_generator/lipsync_video_generator.py
blt/synthesizer/video_generator/Wav2Lip/NOTICE.md
blt/synthesizer/video_generator/Wav2Lip/README.md
blt/synthesizer/video_generator/Wav2Lip/audio.py
blt/synthesizer/video_generator/Wav2Lip/hparams.py
blt/synthesizer/video_generator/Wav2Lip/inference.py
blt/synthesizer/video_generator/Wav2Lip/face_detection/README.md
blt/synthesizer/video_generator/Wav2Lip/face_detection/__init__.py
blt/synthesizer/video_generator/Wav2Lip/face_detection/api.py
blt/synthesizer/video_generator/Wav2Lip/face_detection/models.py
blt/synthesizer/video_generator/Wav2Lip/face_detection/utils.py
blt/synthesizer/video_generator/Wav2Lip/face_detection/detection/__init__.py
blt/synthesizer/video_generator/Wav2Lip/face_detection/detection/core.py
blt/synthesizer/video_generator/Wav2Lip/face_detection/detection/sfd/__init__.py
blt/synthesizer/video_generator/Wav2Lip/face_detection/detection/sfd/bbox.py
blt/synthesizer/video_generator/Wav2Lip/face_detection/detection/sfd/detect.py
blt/synthesizer/video_generator/Wav2Lip/face_detection/detection/sfd/net_s3fd.py
blt/synthesizer/video_generator/Wav2Lip/face_detection/detection/sfd/sfd_detector.py
blt/synthesizer/video_generator/Wav2Lip/models/__init__.py
blt/synthesizer/video_generator/Wav2Lip/models/conv.py
blt/synthesizer/video_generator/Wav2Lip/models/syncnet.py
blt/synthesizer/video_generator/Wav2Lip/models/wav2lip.py
blt/translators/__init__.py
blt/translators/lyrics_translator/__init__.py
blt/translators/lyrics_translator/agent.py
blt/translators/lyrics_translator/config.py
blt/translators/lyrics_translator/graph.py
blt_toolkit-0.1.2.dist-info/METADATA
blt_toolkit-0.1.2.dist-info/WHEEL
blt_toolkit-0.1.2.dist-info/licenses/LICENSE
blt_toolkit-0.1.2.dist-info/RECORD
