Metadata-Version: 2.4
Name: blt-toolkit
Version: 0.1.2
Summary: Better Lyrics Translation Toolkit - AI-powered song translation with music constraint preservation
Project-URL: Homepage, https://github.com/guan404ming/blt
Project-URL: Repository, https://github.com/guan404ming/blt
Project-URL: Issues, https://github.com/guan404ming/blt/issues
Author-email: "Guan-Ming, Chiu" <guanmingchiu@gmail.com>
License: Apache-2.0
License-File: LICENSE
Keywords: AI,NLP,lyrics,music,song,translation
Classifier: Development Status :: 3 - Alpha
Classifier: Intended Audience :: Developers
Classifier: License :: OSI Approved :: Apache Software License
Classifier: Programming Language :: Python :: 3
Classifier: Programming Language :: Python :: 3.11
Classifier: Topic :: Multimedia :: Sound/Audio
Classifier: Topic :: Text Processing :: Linguistic
Requires-Python: >=3.11
Requires-Dist: demucs>=4.0.1
Requires-Dist: gradio-client>=2.0.1
Requires-Dist: hanlp>=2.1.0
Requires-Dist: langchain-core>=1.2.0
Requires-Dist: langchain-ollama>=1.0.1
Requires-Dist: langgraph>=1.0.5
Requires-Dist: librosa>=0.10.0
Requires-Dist: numpy<2.0.0,>=1.26.0
Requires-Dist: openai-whisper>=20250101
Requires-Dist: opencc-python-reimplemented>=0.1.7
Requires-Dist: opencv-python>=4.11.0.86
Requires-Dist: panphon>=0.22.2
Requires-Dist: phonemizer>=3.3.0
Requires-Dist: pydantic-settings>=2.12.0
Requires-Dist: pypinyin>=0.55.0
Requires-Dist: python-dotenv>=1.2.1
Requires-Dist: soundfile>=0.12.0
Requires-Dist: stable-ts>=1.14.7
Requires-Dist: torch>=2.5.0
Requires-Dist: torchaudio>=2.5.0
Provides-Extra: dev
Requires-Dist: mypy>=1.10.0; extra == 'dev'
Requires-Dist: pytest>=8.0.0; extra == 'dev'
Requires-Dist: ruff>=0.4.0; extra == 'dev'
